{
  "db_name": "PostgreSQL",
  "query": "\n        SELECT \n            rank as \"rank!: BallchasingRank\",\n            COUNT(*) FILTER (WHERE download_status = 'not_downloaded') as \"not_downloaded!\",\n            COUNT(*) FILTER (WHERE download_status = 'in_progress') as \"in_progress!\",\n            COUNT(*) FILTER (WHERE download_status = 'downloaded') as \"downloaded!\",\n            COUNT(*) FILTER (WHERE download_status = 'failed') as \"failed!\"\n        FROM ballchasing_replays\n        GROUP BY rank\n        ORDER BY rank\n        ",
  "describe": {
    "columns": [
      {
        "ordinal": 0,
        "name": "rank!: BallchasingRank",
        "type_info": {
          "Custom": {
            "name": "ballchasing_rank",
            "kind": {
              "Enum": [
                "unranked",
                "bronze1",
                "bronze2",
                "bronze3",
                "silver1",
                "silver2",
                "silver3",
                "gold1",
                "gold2",
                "gold3",
                "platinum1",
                "platinum2",
                "platinum3",
                "diamond1",
                "diamond2",
                "diamond3",
                "champion1",
                "champion2",
                "champion3",
                "grand_champion"
              ]
            }
          }
        }
      },
      {
        "ordinal": 1,
        "name": "not_downloaded!",
        "type_info": "Int8"
      },
      {
        "ordinal": 2,
        "name": "in_progress!",
        "type_info": "Int8"
      },
      {
        "ordinal": 3,
        "name": "downloaded!",
        "type_info": "Int8"
      },
      {
        "ordinal": 4,
        "name": "failed!",
        "type_info": "Int8"
      }
    ],
    "parameters": {
      "Left": []
    },
    "nullable": [
      false,
      null,
      null,
      null,
      null
    ]
  },
  "hash": "c155d189409e72d94f33d3fb03655f8c9c91e2b617cbc55c8d6c2d8c3aa7902f"
}
